[
  {
    "station": "Abbey Road",
    "naptanId": "940GZZDLABR"
  },
  {
    "station": "Acton Central",
    "naptanId": "910GACTNCTL"
  },
  {
    "station": "Oxford",
    "naptanId": "940GZZLUOXC"
  },
  {
    "station": "Acton Town",
    "naptanId": "940GZZLUACT"
  },
  {
    "station": "Aldgate East",
    "naptanId": "940GZZLUADE"
  },
  {
    "station": "Aldgate",
    "naptanId": "940GZZLUALD"
  },
  {
    "station": "Alperton",
    "naptanId": "940GZZLUALP"
  },
  {
    "station": "Amersham",
    "naptanId": "940GZZLUAMS"
  },
  {
    "station": "Angel",
    "naptanId": "940GZZLUAGL"
  },
  {
    "station": "Arnos Grove",
    "naptanId": "940GZZLUASG"
  },
  {
    "station": "Arsenal",
    "naptanId": "940GZZLUASL"
  },
  {
    "station": "Baker Street",
    "naptanId": "940GZZLUBST"
  },
  {
    "station": "Balham",
    "naptanId": "940GZZLUBLM"
  },
  {
    "station": "Bank",
    "naptanId": "940GZZLUBNK"
  },
  {
    "station": "Barbican",
    "naptanId": "940GZZLUBBN"
  },
  {
    "station": "Barking",
    "naptanId": "940GZZLUBKG"
  },
  {
    "station": "Barkingside",
    "naptanId": "940GZZLUBKE"
  },
  {
    "station": "Barons Court",
    "naptanId": "940GZZLUBSC"
  },
  {
    "station": "Bayswater",
    "naptanId": "940GZZLUBWT"
  },
  {
    "station": "Becontree",
    "naptanId": "940GZZLUBEC"
  },
  {
    "station": "Belsize Park",
    "naptanId": "940GZZLUBZP"
  },
  {
    "station": "Bermondsey",
    "naptanId": "940GZZLUBMY"
  },
  {
    "station": "Bethnal Green",
    "naptanId": "940GZZLUBLG"
  },
  {
    "station": "",
    "naptanId": ""
  },
  {
    "station": "f",
    "naptanId": "f"
  },
  {
    "station": "f",
    "naptanId": "f"
  },
  {
    "station": "f",
    "naptanId": "f"
  }
]